rigol_dg1022/__init__.py
rigol_dg1022/driver.py
rigol_dg1022-0.1.0.dist-info/licenses/LICENSE
rigol_dg1022-0.1.0.dist-info/METADATA
rigol_dg1022-0.1.0.dist-info/WHEEL
rigol_dg1022-0.1.0.dist-info/top_level.txt
rigol_dg1022-0.1.0.dist-info/RECORD
