Metadata-Version: 2.4
Name: rigol_dg1022
Version: 0.1.0
Summary: A Python driver for Rigol arbitrary signal generators
Author-email: Daniel Köpping <daniel.koepping@de.abb.com>
License-Expression: MIT
Keywords: Rigol DG1022,Rigol DG1062,Rigol DG4102,Python driver,Ethernet,USB,Signal generator,Industrial automation
Classifier: Programming Language :: Python :: 3
Classifier: Operating System :: OS Independent
Requires-Python: >=3.8
License-File: LICENSE
Requires-Dist: pyvisa
Requires-Dist: pyusb
Dynamic: license-file
